no_ppap_milter/__init__.py
no_ppap_milter/cli_no_ppap_milter.py
no_ppap_milter/libemail.py
no_ppap_milter/no_ppap_milter.py
no_ppap_milter-0.2.5.dist-info/entry_points.txt
no_ppap_milter-0.2.5.dist-info/LICENSE
no_ppap_milter-0.2.5.dist-info/WHEEL
no_ppap_milter-0.2.5.dist-info/METADATA
no_ppap_milter-0.2.5.dist-info/RECORD
