Metadata-Version: 2.1
Name: no-ppap-milter
Version: 0.2.5
Summary: This is a milter to prevent receiving emails which has encrypted zip attachments.
Home-page: https://github.com/hirachan/no-ppap-milter
License: MIT
Author: HIRANO Yoshitaka
Author-email: yo@hirano.cc
Requires-Python: >=3.6,<4.0
Classifier: License :: OSI Approved :: MIT License
Classifier: Programming Language :: Python :: 3
Classifier: Programming Language :: Python :: 3.10
Classifier: Programming Language :: Python :: 3.6
Classifier: Programming Language :: Python :: 3.7
Classifier: Programming Language :: Python :: 3.8
Classifier: Programming Language :: Python :: 3.9
Requires-Dist: pymilter (>=1.0.5,<2.0.0)
Project-URL: Repository, https://github.com/hirachan/no-ppap-milter
